{
	"info": {
		"_postman_id": "2a9k86l8-j9j8-4844-9178-264e9864fbc4",
		"name": "Third: Collection",
		"schema": "https://schema.getpostman.com/json/collection/v2.1.0/collection.json",
		"_uid": "539613-2a9k86l8-j9j8-4844-9178-264e9864fbc4"
	},
	"item": [],
	"event": [
		{
			"listen": "prerequest",
			"script": {
				"id": "95cb338b-dd76-464e-9704-884643f4ee59",
				"type": "text/javascript",
				"exec": [
					""
				]
			}
		},
		{
			"listen": "test",
			"script": {
				"id": "225d61c0-b9a8-4c27-a58f-b45f2ac1001e",
				"type": "text/javascript",
				"exec": [
					"// Test"
				]
			}
		}
	]
}